Metadata-Version: 2.1
Name: odoo14-addon-intrastat-product
Version: 14.0.2.1.5
Summary: Base module for Intrastat Product
Home-page: https://github.com/OCA/intrastat-extrastat
Author: ACSONE SA/NV, brain-tec AG, Akretion, Noviat, Odoo Community Association (OCA)
Author-email: support@odoo-community.org
License: AGPL-3
Platform: UNKNOWN
Classifier: Programming Language :: Python
Classifier: Framework :: Odoo
Classifier: Framework :: Odoo :: 14.0
Classifier: License :: OSI Approved :: GNU Affero General Public License v3
Requires-Python: >=3.6
Requires-Dist: odoo14-addon-intrastat-base
Requires-Dist: odoo14-addon-product-harmonized-system
Requires-Dist: odoo14-addon-report-xlsx-helper
Requires-Dist: odoo (<14.1dev,>=14.0a)
Requires-Dist: python-stdnum (>=1.16)
